werobot/__init__.py
werobot/client.py
werobot/config.py
werobot/exceptions.py
werobot/logger.py
werobot/parser.py
werobot/pay.py
werobot/replies.py
werobot/robot.py
werobot/testing.py
werobot/utils.py
werobot/contrib/__init__.py
werobot/contrib/bottle.py
werobot/contrib/django.py
werobot/contrib/error.html
werobot/contrib/flask.py
werobot/contrib/tornado.py
werobot/crypto/__init__.py
werobot/crypto/exceptions.py
werobot/crypto/pkcs7.py
werobot/messages/__init__.py
werobot/messages/base.py
werobot/messages/entries.py
werobot/messages/events.py
werobot/messages/messages.py
werobot/session/__init__.py
werobot/session/filestorage.py
werobot/session/mongodbstorage.py
werobot/session/mysqlstorage.py
werobot/session/postgresqlstorage.py
werobot/session/redisstorage.py
werobot/session/saekvstorage.py
werobot/session/sqlitestorage.py
WeRoBot-1.13.1.dist-info/LICENSE
WeRoBot-1.13.1.dist-info/METADATA
WeRoBot-1.13.1.dist-info/WHEEL
WeRoBot-1.13.1.dist-info/top_level.txt
WeRoBot-1.13.1.dist-info/RECORD
